pybcl-1.0.0.dist-info/top_level.txt
pybcl-1.0.0.dist-info/WHEEL
pybcl-1.0.0.dist-info/entry_points.txt
pybcl-1.0.0.dist-info/METADATA
pybcl-1.0.0.dist-info/LICENSE
pybcl-1.0.0.dist-info/RECORD
pybcl/py.typed
pybcl/_bcl.pyi
pybcl/__init__.py
pybcl/__main__.py
pybcl/_bcl.cpython-312-x86_64-linux-gnu.so
